hello_world/__init__.py
hello_world/chunk_extractor.py
hello_world/decompose.py
hello_world/faiss_ext2.py
hello_world/final_llm.py
hello_world/main.py
hello_world/reranker.py
77_myfirst_hwwo_lib_77_2025_11_8-0.4.6.dist-info/METADATA
77_myfirst_hwwo_lib_77_2025_11_8-0.4.6.dist-info/WHEEL
77_myfirst_hwwo_lib_77_2025_11_8-0.4.6.dist-info/top_level.txt
77_myfirst_hwwo_lib_77_2025_11_8-0.4.6.dist-info/RECORD
