Metadata-Version: 2.4
Name: 77-MyFirst_HwWo-Lib-77_2025_11-8
Version: 0.4.6
Summary: A simple Python library that prints Hello World
Author-email: asnpoatmher <asnpoatmher@gmail.com>
Requires-Python: >=3.6
